async_logstash/__init__.py
async_logstash/base_handler.py
async_logstash/log.py
async_logstash/tcp_handler.py
async_logstash-0.0.1a0.dist-info/LICENSE
async_logstash-0.0.1a0.dist-info/WHEEL
async_logstash-0.0.1a0.dist-info/METADATA
async_logstash-0.0.1a0.dist-info/RECORD
