Metadata-Version: 1.2
Name: async_logstash
Version: 0.0.1a0
Summary: asyncio-compatible logstash logging handler.
Home-page: https://github.com/wikibusiness/async-logstash
License: UNKNOWN
Author: Ocean S.A.
Author-email: osf@wikibusiness.org
Requires-Python: >=3.5
Classifier: Intended Audience :: Developers
Classifier: License :: OSI Approved :: Apache Software License
Classifier: Programming Language :: Python :: 3
Classifier: Programming Language :: Python :: 3.5
Classifier: Programming Language :: Python :: 3.6
Classifier: Topic :: Software Development :: Libraries :: Python Modules
Classifier: Development Status :: 4 - Beta
Classifier: Framework :: AsyncIO
Requires-Dist: tzlocal
Requires-Dist: python-logstash
